ckan/__init__.py
ckan/uploader.py
ckan_uploader/__init__.py
ckan_uploader/uploader.py
rdf_to_html-1.1.0.dist-info/DESCRIPTION.rst
rdf_to_html-1.1.0.dist-info/METADATA
rdf_to_html-1.1.0.dist-info/RECORD
rdf_to_html-1.1.0.dist-info/WHEEL
rdf_to_html-1.1.0.dist-info/entry_points.txt
rdf_to_html-1.1.0.dist-info/metadata.json
rdf_to_html-1.1.0.dist-info/top_level.txt
rdfconv/__init__.py
rdfconv/converter.py
rdfconv/html.py
rdfconv/main.py
rdfconv/objects.py
rdfconv/predicate.py
rdfconv/utils.py
rdfconv/version.py
rdfconv/includes/rdfconv.js
rdfconv/includes/style.css
rdfconv/templates/main.html
rdfconv/templates/node.html
