Metadata-Version: 2.0
Name: rdf-to-html
Version: 1.1.0
Summary: RDF to HTML converter
Home-page: UNKNOWN
Author: Kim Nilsson
Author-email: kim.nilsson@dohi.se
License: EUPL v1.1
Keywords: Open Data,Linked Open Data,RDF,DCAT
Platform: UNKNOWN
Classifier: Development Status :: 5 - Production/Stable
Classifier: Programming Language :: Python :: 2.7
Requires-Dist: ckanapi
Requires-Dist: django (>=1.8.6)
Requires-Dist: pyinotify (>=0.9.6)
Requires-Dist: rdflib (>=4.2.1)
Requires-Dist: requests (>=2.8.1)
